abe_deep_research/__init__.py
abe_deep_research/server.py
abe_deep_research-0.1.1.dist-info/METADATA
abe_deep_research-0.1.1.dist-info/WHEEL
abe_deep_research-0.1.1.dist-info/entry_points.txt
abe_deep_research-0.1.1.dist-info/licenses/LICENSE
abe_deep_research-0.1.1.dist-info/RECORD
