Metadata-Version: 2.4
Name: abe-deep-research
Version: 0.1.1
Summary: A MCP server for deep research and report generation
Author-email: Xing Xing <xing@readingplus.ai>
License-File: LICENSE
Requires-Python: >=3.10
Requires-Dist: mcp>=1.0.0
